setup.py
msg_relay.egg-info/PKG-INFO
msg_relay.egg-info/SOURCES.txt
msg_relay.egg-info/dependency_links.txt
msg_relay.egg-info/requires.txt
msg_relay.egg-info/top_level.txt
relay/__init__.py
relay/channel.py
relay/errors.py
relay/event.py
relay/executor.py
relay/subscriber.py