Metadata-Version: 1.1
Name: msg-relay
Version: 0.0.1
Summary: Lightweight Python publish/subscribe event bus
Home-page: https://github.com/rcrespoa/msgrelay
Author: Roberto Crespo
Author-email: rcrespoa@alumni.nd.edu
License: UNKNOWN
Keywords: pubsub message bus pub sub event
Platform: UNKNOWN
Classifier: Development Status :: 3 - Alpha
Classifier: Intended Audience :: Developers
Classifier: Topic :: Software Development :: Build Tools
Classifier: License :: OSI Approved :: MIT License
Classifier: Programming Language :: Python :: 3.7
Classifier: Programming Language :: Python :: 3.8
Classifier: Programming Language :: Python :: 3.9
